aur_sync_vote/__init__.py
aur_sync_vote/main.py
aur_sync_vote-0.2.2.dist-info/licenses/LICENSE
aur_sync_vote-0.2.2.dist-info/METADATA
aur_sync_vote-0.2.2.dist-info/WHEEL
aur_sync_vote-0.2.2.dist-info/entry_points.txt
aur_sync_vote-0.2.2.dist-info/top_level.txt
aur_sync_vote-0.2.2.dist-info/RECORD
