Metadata-Version: 2.4
Name: aur-sync-vote
Version: 0.2.2
Summary: Automates voting on installed and uninstalled AUR packages
Requires-Python: >=3.10
License-File: LICENSE
Requires-Dist: beautifulsoup4>=4.13.4
Requires-Dist: html5lib>=1.1
Requires-Dist: keyring>=25.7.0
Requires-Dist: requests>=2.32.4
Dynamic: license-file
